{
    "1": {
        "address": "北京市通州区曹园南街",
        "lon": 116.66342052947668,
        "lat": 39.866526542896786
    },
    "2": {
        "address": "北京市丰台区汽车博物馆南路",
        "lon": 116.31562370238125,
        "lat": 39.832995283654284
    },
    "3": {
        "address": "北京市大兴区兴和街",
        "lon": 116.33458433005707,
        "lat": 39.78136183555506
    },
    "4": {
        "address": "北京市朝阳区G101(京密路)",
        "lon": 116.48966171037375,
        "lat": 39.99027389161452
    },
    "5": {
        "address": "北京市朝阳区阜荣街辅路",
        "lon": 116.48776174779154,
        "lat": 39.99331629941643
    },
    "6": {
        "address": "北京市密云区S313",
        "lon": 116.91007932816319,
        "lat": 40.47068410830383
    },
    "7": {
        "address": "北京市朝阳区石各村路",
        "lon": 116.56949185463445,
        "lat": 39.94855090282495
    },
    "8": {
        "address": "北京市大兴区天水大街",
        "lon": 116.32410191177357,
        "lat": 39.683256419378104
    },
    "9": {
        "address": "北京市房山区S326(大件路)",
        "lon": 116.05741930919494,
        "lat": 39.72836984355339
    },
    "10": {
        "address": "北京市丰台区莲花池西路",
        "lon": 116.29428619672126,
        "lat": 39.888867773941094
    },
    "11": {
        "address": "北京市昌平区X003(秦上路)",
        "lon": 116.31531831053358,
        "lat": 40.15719315481518
    },
    "12": {
        "address": "北京市丰台区镇国寺北街",
        "lon": 116.36409028704345,
        "lat": 39.85199580532895
    },
    "13": {
        "address": "北京市昌平区白浮泉路13号",
        "lon": 116.24546983896661,
        "lat": 40.20688794735968
    },
    "14": {
        "address": "北京市丰台区大红门西路35号院-10号楼",
        "lon": 116.38708894403109,
        "lat": 39.84644821637346
    },
    "15": {
        "address": "北京市房山区清苑北街辅路",
        "lon": 116.20348689600023,
        "lat": 39.74077341737744
    },
    "16": {
        "address": "北京市大兴区",
        "lon": 116.42755815336442,
        "lat": 39.824078595586506
    },
    "17": {
        "address": "北京市大兴区福兴街",
        "lon": 116.43011901940908,
        "lat": 39.728132258781216
    },
    "18": {
        "address": "北京市通州区新华西街30号",
        "lon": 116.65538692772382,
        "lat": 39.913548232949346
    },
    "19": {
        "address": "北京市昌平区龙域东一路",
        "lon": 116.32167115868747,
        "lat": 40.0695461023483
    },
    "20": {
        "address": "北京市顺义区",
        "lon": 116.5558362317545,
        "lat": 40.1548723832997
    },
    "21": {
        "address": "北京市西城区手帕口西街3号",
        "lon": 116.34655460803495,
        "lat": 39.897817520768335
    },
    "22": {
        "address": "北京市丰台区",
        "lon": 116.39037660846714,
        "lat": 39.790119081582766
    },
    "23": {
        "address": "北京市通州区新凤河滨河路",
        "lon": 116.54112985539096,
        "lat": 39.75668848820706
    },
    "24": {
        "address": "北京市东城区东直门外大街40号楼1006室",
        "lon": 116.44483843152926,
        "lat": 39.946453652262655
    },
    "25": {
        "address": "北京市大兴区鼎利路",
        "lon": 116.43213232522278,
        "lat": 39.74339085987901
    },
    "26": {
        "address": "北京市大兴区S228(南中轴路)",
        "lon": 116.41462180935535,
        "lat": 39.72389091363594
    },
    "27": {
        "address": "北京市海淀区荷清路",
        "lon": 116.3435971166454,
        "lat": 40.0027128567783
    },
    "28": {
        "address": "北京市朝阳区广顺南大街18号院",
        "lon": 116.48796084076947,
        "lat": 39.99430242222324
    },
    "29": {
        "address": "北京市通州区S303(漷马路旧线)",
        "lon": 116.57745972796198,
        "lat": 39.74573288406249
    },
    "30": {
        "address": "北京市丰台区大瓦窑东二街",
        "lon": 116.24640472413839,
        "lat": 39.86728745728533
    },
    "31": {
        "address": "北京市海淀区中关村北一条17号",
        "lon": 116.32736778728533,
        "lat": 39.99361092837327
    },
    "32": {
        "address": "北京市昌平区Y908(水库南路)",
        "lon": 116.12131059817372,
        "lat": 40.241969934003016
    },
    "33": {
        "address": "北京市朝阳区北四环东路",
        "lon": 116.45655735031741,
        "lat": 39.98999913866414
    },
    "34": {
        "address": "北京市丰台区南三环西路60号",
        "lon": 116.34908991204624,
        "lat": 39.85459355152678
    },
    "35": {
        "address": "北京市房山区X007(大窦路)",
        "lon": 116.07678768425994,
        "lat": 39.682039500051005
    },
    "36": {
        "address": "北京市丰台区银地东路辅路",
        "lon": 116.34215318631144,
        "lat": 39.821678101077346
    },
    "37": {
        "address": "北京市顺义区S307(怀昌路)",
        "lon": 116.54583900895256,
        "lat": 40.25440030637907
    },
    "38": {
        "address": "北京市房山区",
        "lon": 116.02815053584114,
        "lat": 39.70843110151621
    },
    "39": {
        "address": "北京市通州区S201辅路",
        "lon": 116.66638495177538,
        "lat": 39.95747600387673
    },
    "40": {
        "address": "北京市昌平区S321辅路",
        "lon": 116.39067019131815,
        "lat": 40.182245625931365
    },
    "41": {
        "address": "北京市丰台区G104(南苑东路)",
        "lon": 116.41193745323642,
        "lat": 39.81349238807332
    },
    "42": {
        "address": "北京市朝阳区农光南路55号",
        "lon": 116.47435654759232,
        "lat": 39.88557889396924
    },
    "43": {
        "address": "北京市朝阳区",
        "lon": 116.51987967489839,
        "lat": 39.8490707192964
    },
    "44": {
        "address": "北京市通州区运河西大街58号院-2号楼",
        "lon": 116.64561550557042,
        "lat": 39.89739371764581
    },
    "45": {
        "address": "北京市朝阳区朝阳北路",
        "lon": 116.56931806284094,
        "lat": 39.93000958415269
    },
    "46": {
        "address": "北京市石景山区严正街",
        "lon": 116.23976184199357,
        "lat": 39.91184119005315
    },
    "47": {
        "address": "北京市海淀区苏二路",
        "lon": 116.15735565247307,
        "lat": 40.110611933810844
    },
    "48": {
        "address": "北京市通州区经海九路",
        "lon": 116.58829659087674,
        "lat": 39.79644415409173
    },
    "49": {
        "address": "北京市丰台区樊羊路",
        "lon": 116.32040577853162,
        "lat": 39.799478497196965
    },
    "50": {
        "address": "北京市朝阳区大屯路62号",
        "lon": 116.38408246658483,
        "lat": 40.00762285727338
    },
    "51": {
        "address": "北京市丰台区京开东路",
        "lon": 116.35973592259171,
        "lat": 39.84995774859775
    },
    "52": {
        "address": "北京市丰台区广安路37号",
        "lon": 116.31935221351414,
        "lat": 39.89148162990854
    },
    "53": {
        "address": "北京市大兴区魏善庄路",
        "lon": 116.42607376933577,
        "lat": 39.667769953484076
    },
    "54": {
        "address": "北京市大兴区乐园路",
        "lon": 116.32848613309324,
        "lat": 39.77261415702218
    },
    "55": {
        "address": "北京市房山区S317辅路",
        "lon": 116.15436390719701,
        "lat": 39.75129293968782
    },
    "56": {
        "address": "北京市大兴区北兴路",
        "lon": 116.37269144706964,
        "lat": 39.78014044713946
    },
    "57": {
        "address": "北京市大兴区团河路",
        "lon": 116.36785013986513,
        "lat": 39.74356459505404
    },
    "58": {
        "address": "北京市丰台区角门路",
        "lon": 116.3891059226702,
        "lat": 39.85098793598822
    },
    "59": {
        "address": "北京市房山区苏庄西街",
        "lon": 116.12678470451627,
        "lat": 39.73001917982074
    },
    "60": {
        "address": "北京市通州区北苑南路甲42号",
        "lon": 116.65216488156722,
        "lat": 39.90079433527532
    },
    "61": {
        "address": "北京市大兴区",
        "lon": 116.69408033583768,
        "lat": 39.67239872149345
    },
    "62": {
        "address": "北京市昌平区S212(昌赤路)",
        "lon": 116.2381026371108,
        "lat": 40.2743655497892
    },
    "63": {
        "address": "北京市大兴区",
        "lon": 116.42940452956724,
        "lat": 39.82325247939969
    },
    "64": {
        "address": "北京市通州区通惠排干渠绿道",
        "lon": 116.58070481506851,
        "lat": 39.78997141071277
    },
    "65": {
        "address": "北京市大兴区G95(首都环线高速)",
        "lon": 116.65503625624423,
        "lat": 39.655627548862824
    },
    "66": {
        "address": "北京市海淀区成府路",
        "lon": 116.35300237507353,
        "lat": 39.99681600694363
    },
    "67": {
        "address": "北京市朝阳区五元桥",
        "lon": 116.50309226141187,
        "lat": 40.00782520669264
    },
    "68": {
        "address": "北京市昌平区富康路",
        "lon": 116.25206876604045,
        "lat": 40.21779724362826
    },
    "69": {
        "address": "北京市房山区",
        "lon": 116.20321915003304,
        "lat": 39.746708196305896
    },
    "70": {
        "address": "北京市大兴区G3(京台高速)",
        "lon": 116.44375640877946,
        "lat": 39.745244865838565
    },
    "71": {
        "address": "北京市西城区西滨河路1号",
        "lon": 116.36188611708494,
        "lat": 39.94954292619891
    },
    "72": {
        "address": "北京市丰台区莲花池西路",
        "lon": 116.29428619672126,
        "lat": 39.888867773941094
    },
    "73": {
        "address": "北京市西城区兵部洼胡同17号",
        "lon": 116.39444917107329,
        "lat": 39.91018091153016
    },
    "74": {
        "address": "北京市昌平区龙域中街",
        "lon": 116.32469350570909,
        "lat": 40.0704360841176
    },
    "75": {
        "address": "北京市朝阳区金港大道1号",
        "lon": 116.57091264738848,
        "lat": 40.023060395402936
    },
    "76": {
        "address": "北京市朝阳区惠新西街18号b203室",
        "lon": 116.42530999918087,
        "lat": 39.99023859811146
    },
    "77": {
        "address": "北京市房山区X007(大窦路)",
        "lon": 116.07746431712495,
        "lat": 39.679178554449315
    },
    "78": {
        "address": "北京市丰台区西四环南路71号",
        "lon": 116.2891036901934,
        "lat": 39.86035207262716
    },
    "79": {
        "address": "北京市石景山区古城大街3-5号",
        "lon": 116.19298790789183,
        "lat": 39.92226279199617
    },
    "80": {
        "address": "北京市朝阳区西大望路北1号楼",
        "lon": 116.48607189299977,
        "lat": 39.92010674175488
    },
    "81": {
        "address": "北京市东城区东单北大街1-2",
        "lon": 116.42419212746483,
        "lat": 39.92120817466368
    },
    "82": {
        "address": "北京市昌平区朝凤北路",
        "lon": 116.2844754546801,
        "lat": 40.24836879070577
    },
    "83": {
        "address": "北京市朝阳区金港大道1号",
        "lon": 116.57004346218483,
        "lat": 40.02308218347034
    },
    "84": {
        "address": "北京市昌平区龙域南街",
        "lon": 116.32391211146658,
        "lat": 40.069241404969524
    },
    "85": {
        "address": "北京市丰台区",
        "lon": 116.41683017321373,
        "lat": 39.82491604699355
    },
    "86": {
        "address": "北京市房山区长虹西路51号",
        "lon": 116.12921875938281,
        "lat": 39.72924583115293
    },
    "87": {
        "address": "北京市朝阳区西大望路3号院-3",
        "lon": 116.4841667283159,
        "lat": 39.91747314462781
    },
    "88": {
        "address": "北京市顺义区顺平路辅路",
        "lon": 116.6607847156872,
        "lat": 40.122109301123906
    },
    "89": {
        "address": "北京市昌平区神牛路",
        "lon": 116.17832812508411,
        "lat": 40.18616876977163
    },
    "90": {
        "address": "北京市丰台区草桥东路8号",
        "lon": 116.3631464546282,
        "lat": 39.8496809616862
    },
    "91": {
        "address": "北京市顺义区X010(顺白路)",
        "lon": 116.64997587741195,
        "lat": 40.17494425553812
    },
    "92": {
        "address": "北京市房山区广阳西路",
        "lon": 116.15527986817071,
        "lat": 39.7645108351095
    },
    "93": {
        "address": "北京市东城区新中街乙1号",
        "lon": 116.44519414952092,
        "lat": 39.94634407848604
    },
    "94": {
        "address": "北京市丰台区丰广路46号",
        "lon": 116.31145885297606,
        "lat": 39.86389293503798
    },
    "95": {
        "address": "北京市朝阳区百子湾南一路",
        "lon": 116.51145246927825,
        "lat": 39.90569883862823
    },
    "96": {
        "address": "北京市朝阳区广渠路21号院-7",
        "lon": 116.500749689443,
        "lat": 39.900828032635175
    },
    "97": {
        "address": "北京市海淀区马连洼南路",
        "lon": 116.30323887117339,
        "lat": 40.03733916167031
    },
    "98": {
        "address": "北京市朝阳区建国门外大街9号院",
        "lon": 116.4538320606537,
        "lat": 39.914309996101736
    },
    "99": {
        "address": "北京市通州区X012(徐尹路)",
        "lon": 116.76086525170531,
        "lat": 39.996580466744106
    },
    "100": {
        "address": "北京市西城区滨河路",
        "lon": 116.35989114402123,
        "lat": 39.951824141573944
    },
    "101": {
        "address": "北京市丰台区云岗西路",
        "lon": 116.15145024594369,
        "lat": 39.820219335836086
    },
    "102": {
        "address": "北京市朝阳区亮马桥路46号一层",
        "lon": 116.47593150412618,
        "lat": 39.955978715477876
    },
    "103": {
        "address": "北京市朝阳区南沙滩路",
        "lon": 116.39170346378106,
        "lat": 40.005470931093825
    },
    "104": {
        "address": "北京市顺义区裕东路",
        "lon": 116.56359400479738,
        "lat": 40.09649278614387
    },
    "105": {
        "address": "北京市大兴区康定街",
        "lon": 116.54041383850604,
        "lat": 39.776337397003445
    },
    "106": {
        "address": "北京市朝阳区启阳路",
        "lon": 116.4938013045843,
        "lat": 40.00822510035907
    },
    "107": {
        "address": "北京市西城区广安门南街70号",
        "lon": 116.35800395066656,
        "lat": 39.87777553614866
    },
    "108": {
        "address": "北京市顺义区裕美路",
        "lon": 116.55496592297614,
        "lat": 40.09937844626292
    },
    "109": {
        "address": "北京市房山区",
        "lon": 116.02967726219023,
        "lat": 39.70426088758371
    },
    "110": {
        "address": "北京市西城区西直门内大街乙375号",
        "lon": 116.36357909246604,
        "lat": 39.94686143292662
    },
    "111": {
        "address": "北京市朝阳区小营北路23号院-2号楼-105号房",
        "lon": 116.43225682137894,
        "lat": 40.006265015263466
    },
    "112": {
        "address": "北京市丰台区程庄路",
        "lon": 116.27605182321287,
        "lat": 39.86037648069918
    },
    "113": {
        "address": "北京市房山区S326(大件路)",
        "lon": 116.05742733518966,
        "lat": 39.72844182615122
    },
    "114": {
        "address": "北京市通州区文旅路",
        "lon": 116.65661438961139,
        "lat": 39.845729432101315
    },
    "115": {
        "address": "北京市海淀区北太平庄路辅路",
        "lon": 116.3777132412532,
        "lat": 39.97989273010106
    },
    "116": {
        "address": "北京市朝阳区酒仙桥路11号",
        "lon": 116.49581063391571,
        "lat": 39.986292766088745
    },
    "117": {
        "address": "北京市门头沟区上园路",
        "lon": 116.12489001592053,
        "lat": 39.92152897958411
    },
    "118": {
        "address": "北京市丰台区",
        "lon": 116.26749975945492,
        "lat": 39.865629305942875
    },
    "119": {
        "address": "北京市海淀区北四环西路88-17号",
        "lon": 116.28598519402442,
        "lat": 39.97701656945984
    },
    "120": {
        "address": "北京市朝阳区金港北二路",
        "lon": 116.57267520237804,
        "lat": 40.023578498497926
    },
    "121": {
        "address": "北京市顺义区S307(怀昌路)",
        "lon": 116.52846008952076,
        "lat": 40.24220330701113
    },
    "122": {
        "address": "北京市房山区大宁一路",
        "lon": 116.22486589708573,
        "lat": 39.81634177405195
    },
    "123": {
        "address": "北京市顺义区S335辅路",
        "lon": 116.49992448258955,
        "lat": 40.195299627668376
    },
    "124": {
        "address": "北京市丰台区镇国寺北街",
        "lon": 116.36505185584663,
        "lat": 39.852094470249725
    },
    "125": {
        "address": "北京市海淀区",
        "lon": 116.36551810682369,
        "lat": 40.00378118224736
    },
    "126": {
        "address": "北京市顺义区前进街",
        "lon": 116.58151092974265,
        "lat": 40.07719312303724
    },
    "127": {
        "address": "北京市西城区红居南街甲4号",
        "lon": 116.34531437774683,
        "lat": 39.88708787551689
    },
    "128": {
        "address": "北京市昌平区S307(怀昌路)",
        "lon": 116.43326168338172,
        "lat": 40.231905295422365
    },
    "129": {
        "address": "北京市房山区清苑北街辅路",
        "lon": 116.20340920362226,
        "lat": 39.74158054887245
    },
    "130": {
        "address": "北京市大兴区双清巷",
        "lon": 116.34119873085702,
        "lat": 39.75013685312458
    },
    "131": {
        "address": "北京市西城区西直门北大街57号",
        "lon": 116.36284970143811,
        "lat": 39.95223119940591
    },
    "132": {
        "address": "北京市大兴区乐园路",
        "lon": 116.3253993362447,
        "lat": 39.7715838099851
    },
    "133": {
        "address": "北京市朝阳区金港北二路",
        "lon": 116.57232754474332,
        "lat": 40.02296363997124
    },
    "134": {
        "address": "北京市丰台区西四环中路辅路",
        "lon": 116.28400351590832,
        "lat": 39.88992290385417
    },
    "135": {
        "address": "北京市丰台区G104(南苑东路)",
        "lon": 116.41314602388512,
        "lat": 39.81354130612579
    },
    "136": {
        "address": "北京市西城区宣武门东河沿街甲69号",
        "lon": 116.38238272482506,
        "lat": 39.904639019925355
    },
    "137": {
        "address": "北京市大兴区久敬庄路",
        "lon": 116.42970389524349,
        "lat": 39.82511259381853
    }
}